jps_gallery_tools/__init__.py
jps_gallery_tools/_modidx.py
jps_gallery_tools/api.py
jps_gallery_tools/core.py
jps_gallery_tools-0.0.3.dist-info/LICENSE
jps_gallery_tools-0.0.3.dist-info/METADATA
jps_gallery_tools-0.0.3.dist-info/WHEEL
jps_gallery_tools-0.0.3.dist-info/entry_points.txt
jps_gallery_tools-0.0.3.dist-info/top_level.txt
jps_gallery_tools-0.0.3.dist-info/RECORD
